{
        "id": 1,
        "TankName": "风暴坦克",
        "SkillName": "风暴冲锋",
        "SkillIntroduction": "风暴坦克装备了风暴充能引擎，打破了能量守恒定律，可以从失去的能量中重新获取能量来强化机体\n风暴装置充能：坦克移动，攻击命中敌人子弹、单位时都会获得充能值，命中墙壁会减少充能值，充能完成后按能力键可以提升风暴状态\n风暴状态I：坦克的移动速度和攻击力得到小幅提升\n风暴状态II：坦克的移动速度和攻击力得到中幅提升，但是一定时间后会退回风暴状态I并且不可提升至风暴状态III\n风暴状态III：坦克的移动速度和攻击力得到大幅提升并获得护盾",
        "FriendSkillName": "风暴加速",
        "FriendSkillIntroduction": "略微提升友方坦克的移动速度",
        "AttackGap": "0.5f",
        "speed": "3.3f",
        "damage": 1,
        "health": 100,
        "WindStormStatusOneAttack": 1,
        "WindStormStatusOneSpeed": "4.0f;",
        "WindStormStatusTwoAttack": 1,
        "WindStormStatusTwoSpeed": "4.5f",
        "WindStormStatusThreeAttack": 1,
        "WindStormStatusThreeSpeed": "5.0f",
        "ChargeCapacity": "100.0f",
        "MoveCharge": "0.02f",
        "BulletCharge": "2.0f",
        "HitCharge": "3.0f",
        "WallCharge": "-0.1f",
        "WindStromLastTime": "30.0f"
}